artus/__init__.py
artus/data_pre_processing/__init__.py
artus/data_pre_processing/clip_annotated_ortho.py
artus/data_pre_processing/crs_settings.py
artus/data_pre_processing/data_splitting.py
artus/data_pre_processing/tile.py
artus/data_pre_processing/transform_geoson_to_coco.py
artus/evaluate_model/__init__.py
artus/evaluate_model/coco_stats.py
artus/evaluate_model/evaluate.py
artus/evaluate_model/write_eval_results.py
artus/inference/__init__.py
artus/inference/config.py
artus/inference/deploy_unlabeled_dataset.py
artus/inference/predict.py
artus/model_training/__init__.py
artus/model_training/build_trainer.py
artus/model_training/config.py
artus/model_training/data_augmentation.py
artus/model_training/train.py
artus/model_training/validation_hook.py
artus/prepare/__init__.py
artus/prepare/coco_splitting.py
artus/prepare/crs_settings.py
artus/prepare/data_splitting.py
artus/prepare/tile.py
artus/prepare/transform_geojson_to_coco.py
artus/prepare/transform_geoson_to_coco.py
artus/spatialize/GeoCOCOExporter.py
artus/spatialize/GeoFiftyoneExporter.py
artus/spatialize/LocationImporter.py
artus/spatialize/__init__.py
artus/spatialize/export.py
artus/spatialize/spatialize.py
artus/spatialize/spatialize_coco.py
artus/train/__init__.py
artus/train/build_trainer.py
artus/train/config.py
artus/train/data_augmentation.py
artus/train/train.py
artus/train/validation_hook.py
artus-0.3.1.dist-info/LICENSE
artus-0.3.1.dist-info/METADATA
artus-0.3.1.dist-info/WHEEL
artus-0.3.1.dist-info/top_level.txt
artus-0.3.1.dist-info/RECORD
