Metadata-Version: 2.1
Name: artus
Version: 0.3.1
Summary: A geoAI package to train and predict spatial occurences on rasters or georeferenced images.
Author-email: Justine Talpaert Daudon <justine.daudon@protonmail.com>
Project-URL: Homepage, https://github.com/6tronl/artus
Project-URL: Bug Tracker, https://github.com/6tronl/artus/issues
Project-URL: Tutorials, https://github.com/6tronl/artus-examples
Project-URL: Documentation, https://artus.readthedocs.io/en/latest/
Classifier: Programming Language :: Python :: 3
Classifier: Operating System :: OS Independent
Requires-Python: >=3.8
License-File: LICENSE
Requires-Dist: fiftyone (>=0.19.1)
Requires-Dist: torch (>=1.12.1)
Requires-Dist: torchmetrics (>=0.9.3)
Requires-Dist: torchvision (>=0.13.1)
Requires-Dist: geopandas (>=0.13.0)
Requires-Dist: Fiona (==1.8.22)
Requires-Dist: importlib-metadata (==6.1.0)
Requires-Dist: importlib-resources (==5.7.1)
Requires-Dist: joblib (==1.2.0)
Requires-Dist: matplotlib (>=3.5.0)
Requires-Dist: numpy (>=1.18.1)
Requires-Dist: opencv-python (>4.6.0)
Requires-Dist: pandas (>=1.5.2)
Requires-Dist: Pillow (>=9.2.0)
Requires-Dist: plotly (>=5.13.0)
Requires-Dist: pycocotools (>=2.0.6)
Requires-Dist: pylabel (>=0.1.51)
Requires-Dist: pymongo (==4.3.3)
Requires-Dist: PyYAML (>=5.0.0)
Requires-Dist: rasterio (>=1.3.3)
Requires-Dist: scikit-learn (>=1.2.2)
Requires-Dist: scipy (>=1.9.3)
Requires-Dist: shapely (>=1.8.5)
Requires-Dist: tensorboard (>=2.12.0)
Requires-Dist: tqdm (>=4.65.0)
